safaa/Safaa.py
safaa/__init__.py
safaa/configs/train.cfg
safaa/models/__init__.py
safaa/models/false_positive_detection_model.pkl
safaa/models/false_positive_detection_model_sgd.pkl
safaa/models/false_positive_detection_model_sgd.pkl.license
safaa/models/false_positive_detection_vectorizer.pkl
safaa/models/declutter_model/config.cfg
safaa/models/declutter_model/meta.json
safaa/models/declutter_model/tokenizer
safaa/models/declutter_model/ner/cfg
safaa/models/declutter_model/ner/model
safaa/models/declutter_model/ner/moves
safaa/models/declutter_model/tok2vec/cfg
safaa/models/declutter_model/tok2vec/model
safaa/models/declutter_model/vocab/key2row
safaa/models/declutter_model/vocab/lookups.bin
safaa/models/declutter_model/vocab/strings.json
safaa/models/declutter_model/vocab/vectors
safaa/models/declutter_model/vocab/vectors.cfg
safaa/models/entity_recognizer/config.cfg
safaa/models/entity_recognizer/meta.json
safaa/models/entity_recognizer/tokenizer
safaa/models/entity_recognizer/ner/cfg
safaa/models/entity_recognizer/ner/model
safaa/models/entity_recognizer/ner/moves
safaa/models/entity_recognizer/tok2vec/cfg
safaa/models/entity_recognizer/tok2vec/model
safaa/models/entity_recognizer/vocab/key2row
safaa/models/entity_recognizer/vocab/lookups.bin
safaa/models/entity_recognizer/vocab/strings.json
safaa/models/entity_recognizer/vocab/vectors
safaa/models/entity_recognizer/vocab/vectors.cfg
safaa-0.0.3.dist-info/METADATA
safaa-0.0.3.dist-info/WHEEL
safaa-0.0.3.dist-info/top_level.txt
safaa-0.0.3.dist-info/RECORD
