Metadata-Version: 2.1
Name: safaa
Version: 0.0.3
Summary: Created as a part of the 2023 Google Summer of Code project:      Reducing Fossology's False Positive Copyrights, the purpose is to be able      to predict whether a given copyright output from the Fossology software      is a false positive or not. It is also able to remove extra      text from a copyright notice.
Home-page: https://github.com/fossology/safaa
Author: Abdelrahman Jamal
Author-email: abdelrahmanjamal5565@gmail.com
Maintainer: ['Kaushlendra Pratap', 'Gaurav Mishra']
Maintainer-email: ['kaushlendra-pratap.singh@siemens.com', 'mishra.gaurav@siemens.com', 'fossology-devel@fossology.org']
License: UNKNOWN
Platform: UNKNOWN
Classifier: Programming Language :: Python :: 3
Classifier: License :: OSI Approved :: GNU Lesser General Public License v2 (LGPLv2)
Requires-Python: >=3.6
Requires-Dist: spacy==3.8.7
Requires-Dist: joblib==1.5.2
Requires-Dist: pandas==2.3.1
Requires-Dist: scikit-learn==1.6.1
